meow_timetools/__init__.py
meow_timetools/main.py
meow_timetools-0.3.2.dist-info/METADATA
meow_timetools-0.3.2.dist-info/WHEEL
meow_timetools-0.3.2.dist-info/entry_points.txt
meow_timetools-0.3.2.dist-info/top_level.txt
meow_timetools-0.3.2.dist-info/RECORD
