Metadata-Version: 2.1
Name: meow-timetools
Version: 0.3.2
Summary: This is a short description
Home-page: https://link-to-project-webpage.com
Author: you
Author-email: you@gmail.com
License: UNKNOWN
Platform: UNKNOWN
Classifier: Programming Language :: Python :: 3
Requires-Python: >=3.6
Requires-Dist: opencv-python
Requires-Dist: bindings
Requires-Dist: numpy
